MANIFEST.in
README.rst
setup.py
hitch/__init__.py
hitch/commandline.py
hitch/hitchdir.py
hitch/languagestrings.py
hitch.egg-info/PKG-INFO
hitch.egg-info/SOURCES.txt
hitch.egg-info/dependency_links.txt
hitch.egg-info/entry_points.txt
hitch.egg-info/not-zip-safe
hitch.egg-info/top_level.txt
hitch/click/__init__.py
hitch/click/_bashcomplete.py
hitch/click/_compat.py
hitch/click/_termui_impl.py
hitch/click/_textwrap.py
hitch/click/core.py
hitch/click/decorators.py
hitch/click/exceptions.py
hitch/click/formatting.py
hitch/click/globals.py
hitch/click/parser.py
hitch/click/termui.py
hitch/click/testing.py
hitch/click/types.py
hitch/click/utils.py