Metadata-Version: 1.1
Name: hitch
Version: 0.5.7
Summary: Bootstrapper for hitchtest - the loosely coupled integration testing framework
Home-page: https://hitchtest.readthedocs.org/
Author: Colm O'Connor
Author-email: colm.oconnor.github@gmail.com
License: AGPL
Keywords: hitch testing framework bdd tdd declarative tests bootstrap virtualenv
Platform: UNKNOWN
Classifier: Development Status :: 3 - Alpha
Classifier: Intended Audience :: Developers
Classifier: License :: OSI Approved :: GNU Affero General Public License v3 or later (AGPLv3+)
Classifier: Topic :: Software Development :: Quality Assurance
Classifier: Topic :: Software Development :: Testing
Classifier: Topic :: Software Development :: Libraries
Classifier: Operating System :: Unix
Classifier: Environment :: Console
Classifier: Programming Language :: Python :: 2
Classifier: Programming Language :: Python :: 2.6
Classifier: Programming Language :: Python :: 2.7
Classifier: Programming Language :: Python :: 3
Classifier: Programming Language :: Python :: 3.4
